verity_ai_client-0.1.2.dist-info/licenses/LICENSE
verity_ai_pyc/__init__.py
verity_ai_pyc/api_client.py
verity_ai_pyc/api_response.py
verity_ai_pyc/configuration.py
verity_ai_pyc/exceptions.py
verity_ai_pyc/py.typed
verity_ai_pyc/rest.py
verity_ai_pyc/api/__init__.py
verity_ai_pyc/api/agents_api.py
verity_ai_pyc/api/completions_api.py
verity_ai_pyc/api/file_management_api.py
verity_ai_pyc/api/models_api.py
verity_ai_pyc/api/structured_api.py
verity_ai_pyc/api/unstructured_api.py
verity_ai_pyc/models/__init__.py
verity_ai_pyc/models/agent_create_public.py
verity_ai_pyc/models/agent_response.py
verity_ai_pyc/models/agent_update_public.py
verity_ai_pyc/models/chat_completion_message.py
verity_ai_pyc/models/chat_completion_request_public.py
verity_ai_pyc/models/chat_completion_response.py
verity_ai_pyc/models/crawler_job_request_public.py
verity_ai_pyc/models/crawler_job_response.py
verity_ai_pyc/models/crawler_job_status_response.py
verity_ai_pyc/models/create_session_payload.py
verity_ai_pyc/models/delete_request.py
verity_ai_pyc/models/delete_response.py
verity_ai_pyc/models/error_response.py
verity_ai_pyc/models/file_info.py
verity_ai_pyc/models/http_validation_error.py
verity_ai_pyc/models/knowledge_base.py
verity_ai_pyc/models/knowledge_base1.py
verity_ai_pyc/models/knowledge_base2.py
verity_ai_pyc/models/list_files_pagination.py
verity_ai_pyc/models/list_files_response.py
verity_ai_pyc/models/message.py
verity_ai_pyc/models/next_token.py
verity_ai_pyc/models/retrieval_request_public.py
verity_ai_pyc/models/upload_file_response.py
verity_ai_pyc/models/usage.py
verity_ai_pyc/models/user_details_request.py
verity_ai_pyc/models/validate_docs_request.py
verity_ai_pyc/models/validate_docs_response.py
verity_ai_pyc/models/validation_error.py
verity_ai_pyc/models/validation_error_loc_inner.py
verity_ai_client-0.1.2.dist-info/METADATA
verity_ai_client-0.1.2.dist-info/WHEEL
verity_ai_client-0.1.2.dist-info/top_level.txt
verity_ai_client-0.1.2.dist-info/RECORD
