Metadata-Version: 2.4
Name: verity-ai-client
Version: 0.1.2
Summary: Official Python client for Verity AI - Comprehensive API service for unstructured and structured RAG generation, file management, and AI interactions
Home-page: https://veritylabs.ai
Author: Verity Labs
Author-email: support@veritylabs.ai
Maintainer: Verity Labs
Maintainer-email: support@veritylabs.ai
License: MIT
Project-URL: Homepage, https://veritylabs.ai
Project-URL: Documentation, https://docs.veritylabs.ai
Project-URL: Repository, https://github.com/veritylabs/verity-ai-python-client
Project-URL: Bug Tracker, https://github.com/veritylabs/verity-ai-python-client/issues
Project-URL: Changelog, https://github.com/veritylabs/verity-ai-python-client/blob/main/CHANGELOG.md
Keywords: verity-ai,rag,retrieval-augmented-generation,ai,machine-learning,nlp,document-processing,knowledge-base,openapi,api-client
Classifier: Development Status :: 4 - Beta
Classifier: Intended Audience :: Developers
Classifier: Intended Audience :: Science/Research
Classifier: Operating System :: OS Independent
Classifier: Programming Language :: Python :: 3
Classifier: Programming Language :: Python :: 3.9
Classifier: Programming Language :: Python :: 3.10
Classifier: Programming Language :: Python :: 3.11
Classifier: Programming Language :: Python :: 3.12
Classifier: Topic :: Scientific/Engineering :: Artificial Intelligence
Classifier: Topic :: Software Development :: Libraries :: Python Modules
Classifier: Topic :: Internet :: WWW/HTTP :: Dynamic Content
Classifier: Typing :: Typed
Requires-Python: >=3.9
License-File: LICENSE
Requires-Dist: urllib3<3.0.0,>=2.1.0
Requires-Dist: python-dateutil>=2.8.2
Requires-Dist: pydantic>=2.0.0
Requires-Dist: typing-extensions>=4.7.1
Provides-Extra: dev
Requires-Dist: pytest>=7.2.1; extra == "dev"
Requires-Dist: pytest-cov>=2.8.1; extra == "dev"
Requires-Dist: tox>=3.9.0; extra == "dev"
Requires-Dist: flake8>=4.0.0; extra == "dev"
Requires-Dist: types-python-dateutil>=2.8.19.14; extra == "dev"
Requires-Dist: mypy>=1.5; extra == "dev"
Requires-Dist: black>=22.0.0; extra == "dev"
Requires-Dist: isort>=5.0.0; extra == "dev"
Provides-Extra: examples
Requires-Dist: python-dotenv>=1.0.0; extra == "examples"
Dynamic: author
Dynamic: author-email
Dynamic: classifier
Dynamic: description
Dynamic: description-content-type
Dynamic: home-page
Dynamic: keywords
Dynamic: license
Dynamic: license-file
Dynamic: maintainer
Dynamic: maintainer-email
Dynamic: project-url
Dynamic: provides-extra
Dynamic: requires-dist
Dynamic: requires-python
Dynamic: summary
